xtal2png/__init__.py
xtal2png/cli.py
xtal2png/core.py
xtal2png/utils/HKUST-1.cif
xtal2png/utils/README.md
xtal2png/utils/V2NiSe4.cif
xtal2png/utils/Zn2B2PbO6.cif
xtal2png/utils/__init__.py
xtal2png/utils/data.py
xtal2png/utils/mp_cifs.bib
xtal2png/utils/plotting.py
xtal2png-0.9.4.dist-info/LICENSE.txt
xtal2png-0.9.4.dist-info/METADATA
xtal2png-0.9.4.dist-info/WHEEL
xtal2png-0.9.4.dist-info/entry_points.txt
xtal2png-0.9.4.dist-info/top_level.txt
xtal2png-0.9.4.dist-info/RECORD
