Metadata-Version: 2.1
Name: xtal2png
Version: 0.9.4
Summary: Encode and decode crystal structures via portable networks graphics (PNG) files.
Home-page: https://github.com/sparks-baird/xtal2png/
Author: sgbaird
Author-email: sterling.baird@utah.edu
License: MIT
Project-URL: Documentation, https://xtal2png.readthedocs.io
Project-URL: Source, https://github.com/sparks-baird/xtal2png
Project-URL: Tracker, https://github.com/sparks-baird/xtal2png/issues
Project-URL: Conda-Forge, https://anaconda.org/conda-forge/xtal2png
Project-URL: Download, https://pypi.org/project/xtal2png/#files
Project-URL: Twitter, https://twitter.com/xtal2png
Platform: any
Classifier: Development Status :: 4 - Beta
Classifier: Programming Language :: Python
Requires-Python: >=3.6
License-File: LICENSE.txt
Requires-Dist: numpy
Requires-Dist: pillow
Requires-Dist: pymatgen
Requires-Dist: plotly
Requires-Dist: kaleido
Requires-Dist: element-coder
Requires-Dist: click
Requires-Dist: importlib-metadata ; python_version < "3.8"
Provides-Extra: relax
Requires-Dist: m3gnet ; extra == 'relax'
Provides-Extra: testing
Requires-Dist: setuptools ; extra == 'testing'
Requires-Dist: pytest ; extra == 'testing'
Requires-Dist: pytest-cov ; extra == 'testing'
Requires-Dist: m3gnet ; extra == 'testing'
